lorenz_phase_space/__init__.py
lorenz_phase_space/phase_diagrams.py
tests/__init__.py
tests/test_lps.py
lorenz_phase_space-1.4.1.dist-info/LICENSE
lorenz_phase_space-1.4.1.dist-info/METADATA
lorenz_phase_space-1.4.1.dist-info/WHEEL
lorenz_phase_space-1.4.1.dist-info/top_level.txt
lorenz_phase_space-1.4.1.dist-info/RECORD
