Metadata-Version: 2.1
Name: lorenz-phase-space
Version: 1.4.1
Summary: Visualization tool designed to analyze and illustrate the Lorenz Energy Cycle for atmospheric science.
Author: Danilo Couto de Souza
Author-email: danilo.oceano@gmail.com
License: MIT
Keywords: lorenz,energy cycle,atmospheric science,cyclone,baroclinic,barotropic,visualization
Classifier: Development Status :: 4 - Beta
Classifier: Intended Audience :: Science/Research
Classifier: Intended Audience :: Developers
Classifier: License :: OSI Approved :: MIT License
Classifier: Programming Language :: Python :: 3
Classifier: Programming Language :: Python :: 3.8
Classifier: Programming Language :: Python :: 3.9
Classifier: Programming Language :: Python :: 3.10
Classifier: Programming Language :: Python :: 3.11
Classifier: Programming Language :: Python :: 3.12
Classifier: Topic :: Scientific/Engineering :: Atmospheric Science
Classifier: Topic :: Scientific/Engineering :: Visualization
Requires-Python: >=3.8
License-File: LICENSE
Requires-Dist: pandas
Requires-Dist: matplotlib
Requires-Dist: numpy
Requires-Dist: cmocean
